{"contents": [
	{
		"titl": "Демо Web - ресурсы, сделанные во время прохождения практики",
		"col" : "880",
		"prjs" : [
			{
				"nam" : "Kaz-internet - управление тарифами",
				"desc" : "Веб ресурс позволяющий управлять тарифами доступа интернет",
				"dd": "Разработанн в качестве дипломной работы и прохождения практики",
				"link" : "DemoWeb/kaz-internet/",
				"img" : "images/kaz-internet.png",
				"col" : ""
			},
			{
				"nam" : "Онлайн магазин Emarket",
				"desc" : "Онлайн магазин компьютерной электоники",
				"dd": "Разработанн во время прохождения практики от университета",
				"link" : "DemoWeb/Emarket/",
				"img" : "images/Emarket.png",
				"col" : ""
			},
			{
				"nam" : "АРМ сотрудника кафеды.",
				"desc" : "Позволяет преподователям ВУЗа управление документацией учебных планов групп",
				"dd": "Разработанн для кафедры университета",
				"link" : "DemoWeb/isemd/",
				"img" : "images/isemd.png",
				"col" : ""
			},
			{
				"nam" : "БД ВУ ОАП УВД",
				"desc" : "Мониторинг и управление выдачей водительских удостоверений ОАП УВД",
				"dd": "Разработанн во время прохождения практики от университета",
				"link" : "DemoWeb/practika-db-vu/",
				"img" : "images/practika-db-vu.png",
				"col" : ""
			}
		]
	},
	{
		"titl": "JS проекты",
		"col" : "880",
		"prjs" : [
			{
				"nam" : "Eval - калькулятор",
				"desc" : "Консольный онлайн калькулятор работающий на основе функции Eval()",
				"dd": "",
				"link" : "JSProj/Eval.html",
				"img" : "images/Eval.png",
				"col" : ""
			},
			{
				"nam" : "Программа для шифрования методом квадратов",
				"desc" : "Является оригинальным инструментом простого шифрования.",
				"dd": "Разработанна во время учебы просто так)",
				"link" : "JSProj/cipher.html",
				"img" : "images/cipher.png",
				"col" : ""
			},
			{
				"nam" : "Другие проекты",
				"desc" : "",
				"dd": "",
				"link" : "JSProj/",
				"img" : "images/404.png",
				"col" : ""
			}
		]
	},
	{
		"titl": "Наработки для игр",
		"col" : "880",
		"prjs" : [
			{
				"nam" : "Проги для построения моделек для игры ScrapMechanic",
				"desc" : "Проги для построения моделек для игры ScrapMechanic",
				"dd": "Просто так",
				"link" : "CusGame/ScrMech/",
				"img" : "images/ScrMech.png",
				"col" : ""
			},
			{
				"nam" : "Разработанные игры и програмки",
				"desc" : " Игры разработанны на программе GameMaker",
				"dd": "Разработанно в школьные годы",
				"link" : "CusGame/GM/",
				"img" : "images/GM.png",
				"col" : ""
			}
		]
	}
]}